gqlient/__init__.py
gqlient/cli.py
gqlient/generator.py
gqlient/templates/all_types.py.jinja2
gqlient/templates/client.py.jinja2
gqlient/templates/common.py.jinja2
gqlient/templates/enum_types.py.jinja2
gqlient/templates/input_types.py.jinja2
gqlient/templates/mutation.py.jinja2
gqlient/templates/pyproject.toml.jinja2
gqlient/templates/query.py.jinja2
gqlient/templates/queryable_types.py.jinja2
gqlient/templates/result_types.py.jinja2
gqlient/type_utils.py
graphqlient-0.0.1a3.dist-info/METADATA
graphqlient-0.0.1a3.dist-info/WHEEL
graphqlient-0.0.1a3.dist-info/RECORD
