Metadata-Version: 2.1
Name: graphqlient
Version: 0.0.1a3
Summary: :)
Author: Vojtěch Dohnal
Author-email: vojdoh@gmail.com
Requires-Python: >=3.9,<4.0
Classifier: Programming Language :: Python :: 3
Classifier: Programming Language :: Python :: 3.9
Classifier: Programming Language :: Python :: 3.10
Classifier: Programming Language :: Python :: 3.11
Requires-Dist: Jinja2 (>=3.1.2,<4.0.0)
Requires-Dist: gql[aiohttp,requests] (>=3.4.0,<4.0.0)
Requires-Dist: inflection (>=0.5.1,<0.6.0)
Requires-Dist: typer (>=0.7.0,<0.8.0)
